{
  "byte_length": 1874166,
  "company_slug": "paypal",
  "content_type": "text/html; charset=utf-8",
  "fetched_at": "2026-04-24T07:54:23.001490+00:00",
  "http_status": 200,
  "policy_kind": "privacy_policy",
  "policy_label": "PayPal Privacy Statement (US)",
  "policy_region": "US",
  "sha256": "c442d01b121f903f71e2a2d1ad1439aee32f9a2211bc8898ccb94dd6374ecc2f",
  "snapshot_date": "2026-04-24",
  "source": "live",
  "text_length": 43080,
  "url": "https://www.paypal.com/us/legalhub/privacy-full"
}
